Metadata-Version: 2.1
Name: plateFinder_Eneda
Version: 1.0.1
Summary: A package to find the plate
Author: Eneda Zela
Keywords: plateFinder,plate,
Classifier: Development Status :: 1 - Planning
Classifier: Intended Audience :: Developers
Classifier: Programming Language :: Python :: 3
Classifier: Operating System :: Unix
Classifier: Operating System :: MacOS :: MacOS X
Classifier: Operating System :: Microsoft :: Windows
Requires-Dist: openpyxl
Requires-Dist: pandas
